HISTORY.txt
README.txt
ez_setup.py
setup.cfg
setup.py
src/ClueMapperSecure.egg-info/PKG-INFO
src/ClueMapperSecure.egg-info/SOURCES.txt
src/ClueMapperSecure.egg-info/dependency_links.txt
src/ClueMapperSecure.egg-info/namespace_packages.txt
src/ClueMapperSecure.egg-info/requires.txt
src/ClueMapperSecure.egg-info/top_level.txt
src/ClueMapperSecure.egg-info/zip-safe
src/clue/__init__.py
src/clue/secure/__init__.py
src/clue/secure/auth.py
src/clue/secure/htpasswd.py
src/clue/secure/tests.py
src/clue/secure/templates/login.html