Metadata-Version: 1.0
Name: ClueMapperSecure
Version: 0.6.3
Summary: Security component for ClueMapper.
Home-page: http://projects.serverzen.com/pm/p/cluemapper
Author: Rocky Burt
Author-email: rocky@serverzen.com
License: BSD
Platform: UNKNOWN
Classifier: Programming Language :: Python
Classifier: Topic :: Software Development :: Libraries :: Python Modules
